pte/__init__.py
pte/filetools/__init__.py
pte/filetools/bids.py
pte/filetools/events.py
pte/filetools/filefinder.py
pte/filetools/matlab.py
pte/pipelines/__init__.py
pte/pipelines/pipelines.py
pte/plotting/__init__.py
pte/plotting/clusterplot.py
pte/plotting/coordinates.py
pte/plotting/meshplot.py
pte/plotting/raw.py
pte/plotting/resources/TDdatabase.mat
pte/plotting/resources/faces.mat
pte/plotting/resources/grid.mat
pte/plotting/resources/mni_hull.mat
pte/plotting/resources/stn_surf.mat
pte/plotting/resources/vertices.mat
pte/preprocessing/__init__.py
pte/preprocessing/annotation.py
pte/preprocessing/channels.py
pte/preprocessing/emg.py
pte/preprocessing/preprocessing.py
pte/time_frequency/__init__.py
pte/time_frequency/bursts.py
pte/time_frequency/power.py
pte-0.2.0.dist-info/METADATA
pte-0.2.0.dist-info/WHEEL
pte-0.2.0.dist-info/licenses/LICENSE
pte-0.2.0.dist-info/RECORD
