Metadata-Version: 2.1
Name: pte
Version: 0.2.0
Summary: An open-source software package for working with electrophysiological data
Project-URL: bugtracker, https://github.com/richardkoehler/pte/issues
Project-URL: changelog, https://github.com/richardkoehler/pte/blob/main/docs/CHANGELOG.md
Project-URL: repository, https://github.com/richardkoehler/pte
Author: Richard M. Köhler
Maintainer: Richard M. Köhler
License: MIT License
License-File: LICENSE
Keywords: dbs,ecog,eeg,ieeg,lfp,neurophysiology
Classifier: Development Status :: 2 - Pre-Alpha
Classifier: Intended Audience :: Developers
Classifier: Intended Audience :: Science/Research
Classifier: License :: OSI Approved :: MIT License
Classifier: Operating System :: OS Independent
Classifier: Programming Language :: Python
Classifier: Programming Language :: Python :: 3
Classifier: Programming Language :: Python :: 3 :: Only
Classifier: Programming Language :: Python :: 3.10
Classifier: Topic :: Scientific/Engineering
Classifier: Topic :: Software Development :: Libraries :: Python Modules
Classifier: Typing :: Typed
Requires-Python: >=3.10
Requires-Dist: joblib
Requires-Dist: matplotlib
Requires-Dist: mne-bids
Requires-Dist: mne-qt-browser
Requires-Dist: mne[hdf5]>=1.0
Requires-Dist: numba
Requires-Dist: numpy
Requires-Dist: pandas
Requires-Dist: plotly
Requires-Dist: pte-stats
Requires-Dist: pybv
Requires-Dist: pyqt5
Requires-Dist: scikit-image
Requires-Dist: scipy
Provides-Extra: dev
Requires-Dist: black; extra == 'dev'
Requires-Dist: hatch; extra == 'dev'
Requires-Dist: mypy; extra == 'dev'
Requires-Dist: packaging; extra == 'dev'
Requires-Dist: pre-commit; extra == 'dev'
Requires-Dist: pytest; extra == 'dev'
Requires-Dist: pytest-cov; extra == 'dev'
Requires-Dist: ruff; extra == 'dev'
Requires-Dist: tox; extra == 'dev'
